multi_form_view/__init__.py
multi_form_view/base.py
django_multi_form_view-2.0.1.dist-info/LICENSE
django_multi_form_view-2.0.1.dist-info/METADATA
django_multi_form_view-2.0.1.dist-info/WHEEL
django_multi_form_view-2.0.1.dist-info/top_level.txt
django_multi_form_view-2.0.1.dist-info/RECORD
