Metadata-Version: 1.0
Name: django-multi-form-view
Version: 2.0.1
Summary: Class based views for handling more than one form in a single view
Home-page: https://github.com/TimBest/django-multi-form-view
Author: Tim Best
Author-email: UNKNOWN
License: GNU licence, see LICENCE
Platform: UNKNOWN
